Metadata-Version: 1.0
Name: diceset
Version: 0.1
Summary: A simple dice set creator and roller.
Home-page: UNKNOWN
Author: Alexandru Gradinaru
Author-email: gradinaru.alex@gmail.com
License: UNKNOWN
Platform: UNKNOWN
